fxdayu_data/DataAPI.py
fxdayu_data/DataConfig.py
fxdayu_data/__init__.py
fxdayu_data/api_console.py
fxdayu_data/commands.py
fxdayu_data/config.py
fxdayu_data/default.py
fxdayu_data/entry_point.py
fxdayu_data/examples.py
fxdayu_data/collector/__init__.py
fxdayu_data/collector/oanda.py
fxdayu_data/collector/oanda_api.py
fxdayu_data/collector/quests.py
fxdayu_data/collector/sina_tick.py
fxdayu_data/collector/wmcloud_api.py
fxdayu_data/costume/__init__.py
fxdayu_data/costume/basic.py
fxdayu_data/costume/utils.py
fxdayu_data/costume/file/FileCostume.py
fxdayu_data/costume/file/FileTarget.py
fxdayu_data/costume/file/__init__.py
fxdayu_data/costume/mongo/__init__.py
fxdayu_data/costume/mongo/costume.py
fxdayu_data/costume/mongo/target.py
fxdayu_data/data_api/__init__.py
fxdayu_data/data_api/bonus.py
fxdayu_data/data_api/candle.py
fxdayu_data/data_api/factor.py
fxdayu_data/data_api/basic/__init__.py
fxdayu_data/data_api/basic/adjust.py
fxdayu_data/data_api/basic/candle.py
fxdayu_data/data_api/basic/factor.py
fxdayu_data/data_api/basic/info.py
fxdayu_data/data_api/bundle/__init__.py
fxdayu_data/data_api/bundle/adjust.py
fxdayu_data/data_api/bundle/blp_api.py
fxdayu_data/data_api/bundle/blp_reader.py
fxdayu_data/data_api/bundle/candle.py
fxdayu_data/data_api/bundle/default.py
fxdayu_data/data_api/bundle/factor.py
fxdayu_data/data_api/bundle/info.py
fxdayu_data/data_api/mongo/__init__.py
fxdayu_data/data_api/mongo/adjust.py
fxdayu_data/data_api/mongo/candle.py
fxdayu_data/data_api/mongo/factor.py
fxdayu_data/data_api/mongo/info.py
fxdayu_data/data_api/mongo/reader.py
fxdayu_data/handler/__init__.py
fxdayu_data/handler/base.py
fxdayu_data/handler/bundle.py
fxdayu_data/handler/mongo_handler.py
fxdayu_data/handler/redis_handler.py
fxdayu_data/tools/__init__.py
fxdayu_data/tools/convert.py
fxdayu_data/tools/decorators.py
fxdayu_data/tools/pandas_tools.py
fxdayu_data/tools/resampler.py
fxdayu_data-0.2.6.7.dist-info/DESCRIPTION.rst
fxdayu_data-0.2.6.7.dist-info/METADATA
fxdayu_data-0.2.6.7.dist-info/RECORD
fxdayu_data-0.2.6.7.dist-info/WHEEL
fxdayu_data-0.2.6.7.dist-info/entry_points.txt
fxdayu_data-0.2.6.7.dist-info/metadata.json
fxdayu_data-0.2.6.7.dist-info/top_level.txt
