Metadata-Version: 2.0
Name: fxdayu-data
Version: 0.2.6.7
Summary: UNKNOWN
Home-page: https://github.com/cheatm/fxdayu_data.git
Author: Cam
Author-email: cam@fxdayu.com
License: Apache License v2
Platform: UNKNOWN
Requires-Dist: backports.functools-lru-cache (>=1.4)
Requires-Dist: bcolz (==1.1.2)
Requires-Dist: click (>=6.7)
Requires-Dist: lxml (>=3.7.3)
Requires-Dist: numpy (>=1.11.0)
Requires-Dist: pandas (>=0.18.1)
Requires-Dist: pymongo (==3.4.0)
Requires-Dist: redis (>=2.10.5)
